nmslib.cp314-win_amd64.pyd
nmslib-2.1.2.dist-info/licenses/LICENSE
nmslib-2.1.2.dist-info/licenses/LICENSE-Apache-2.0
nmslib-2.1.2.dist-info/METADATA
nmslib-2.1.2.dist-info/WHEEL
nmslib-2.1.2.dist-info/top_level.txt
nmslib-2.1.2.dist-info/RECORD
