Metadata-Version: 2.4
Name: nmslib
Version: 2.1.2
Summary: Non-Metric Space Library (NMSLIB)
Home-page: https://github.com/nmslib/nmslib
Author: B. Naidan, L. Boytsov, Yu. Malkov, B. Frederickson, D. Novak, et al.
License-File: LICENSE
License-File: LICENSE-Apache-2.0
Requires-Dist: pybind11>=2.2.3
Requires-Dist: scipy
Requires-Dist: numpy>=1.10.0; python_version >= "3.5"
Dynamic: author
Dynamic: description
Dynamic: home-page
Dynamic: license-file
Dynamic: requires-dist
Dynamic: summary
